keyvault.py
ams_opdrachten_team_utils-0.2.dist-info/LICENSE
ams_opdrachten_team_utils-0.2.dist-info/METADATA
ams_opdrachten_team_utils-0.2.dist-info/WHEEL
ams_opdrachten_team_utils-0.2.dist-info/top_level.txt
ams_opdrachten_team_utils-0.2.dist-info/RECORD
