Metadata-Version: 2.1
Name: ams-opdrachten-team-utils
Version: 0.2
Summary: A library to contain common code for the AMS Opdrachten team
Author-email: Jeroen Beekman <j.beekman@amsterdam.nl>
License: Mozilla Public License
Project-URL: Homepage, https://github.com/Amsterdam/ams-opdrachten-team-utils
Project-URL: Bug Tracker, https://github.com/Amsterdam/ams-opdrachten-team-utils/issues
Classifier: Programming Language :: Python :: 3
Classifier: License :: OSI Approved :: MIT License
Classifier: Operating System :: OS Independent
Requires-Python: >=3.9
License-File: LICENSE
